cobli_logging/__init__.py
cobli_logging/config.py
cobli_logging/formatter.py
cobli_logging_formatter-1.0.1.dist-info/METADATA
cobli_logging_formatter-1.0.1.dist-info/WHEEL
cobli_logging_formatter-1.0.1.dist-info/licenses/LICENSE
cobli_logging_formatter-1.0.1.dist-info/RECORD
