Metadata-Version: 2.4
Name: cobli-logging-formatter
Version: 1.0.1
Summary: A structured JSON logging formatter with Datadog integration
Project-URL: Homepage, https://github.com/Cobliteam/cobli-logging-formatter
Project-URL: Documentation, https://github.com/Cobliteam/cobli-logging-formatter#readme
Project-URL: Repository, https://github.com/Cobliteam/cobli-logging-formatter.git
Project-URL: Issues, https://github.com/Cobliteam/cobli-logging-formatter/issues
Author: Cobli Development Team
License: MIT License
License-File: LICENSE
Keywords: datadog,formatter,json,logging,structured-logging
Classifier: Development Status :: 5 - Production/Stable
Classifier: Intended Audience :: Developers
Classifier: License :: OSI Approved :: MIT License
Classifier: Operating System :: OS Independent
Classifier: Programming Language :: Python :: 3
Classifier: Programming Language :: Python :: 3.8
Classifier: Programming Language :: Python :: 3.9
Classifier: Programming Language :: Python :: 3.10
Classifier: Programming Language :: Python :: 3.11
Classifier: Programming Language :: Python :: 3.12
Classifier: Topic :: Software Development :: Libraries :: Python Modules
Classifier: Topic :: System :: Logging
Requires-Python: >=3.8
Requires-Dist: ddtrace>=1.0.0
Provides-Extra: dev
Requires-Dist: black>=22.0; extra == 'dev'
Requires-Dist: flake8>=4.0; extra == 'dev'
Requires-Dist: mypy>=0.900; extra == 'dev'
Requires-Dist: pytest-cov>=2.0; extra == 'dev'
Requires-Dist: pytest>=6.0; extra == 'dev'
Requires-Dist: twine>=4.0; extra == 'dev'
